NLPUtilsBERT/Utils_NLP_EDA.py
NLPUtilsBERT/Utils_TextClassification_BERT.py
NLPUtilsBERT/__init__.py
nlputilsbert-0.0.4.dist-info/LICENSE
nlputilsbert-0.0.4.dist-info/METADATA
nlputilsbert-0.0.4.dist-info/WHEEL
nlputilsbert-0.0.4.dist-info/top_level.txt
nlputilsbert-0.0.4.dist-info/RECORD
