Metadata-Version: 2.2
Name: NLPUtilsBERT
Version: 0.0.4
Summary: Common Utilities
Home-page: https://github.com/AeroVikas/NLPUtilsBERT.git
Download-URL: https://github.com/AeroVikas/NLPUtilsBERT.git
Author: Vikas Goel
Author-email: vikas.aero@gmail.com
Maintainer: Vikas Goel
Maintainer-email: vikas.aero@gmail.com
License: MIT
Project-URL: Bug Tracker, https://github.com/pypa/sampleproject/issues
Keywords: Furuness,Login,login,terminal
Classifier: Intended Audience :: Developers
Classifier: License :: OSI Approved :: MIT License
Classifier: Operating System :: OS Independent
Classifier: Programming Language :: Python :: 3
Requires-Python: >=3.11.9
License-File: LICENSE
Requires-Dist: pandas==2.2.3
Requires-Dist: seaborn==0.13.2
Requires-Dist: spacy==3.8.4
Requires-Dist: wordcloud==1.9.4
Requires-Dist: torch==2.6.0
Requires-Dist: scikit_learn==1.6.1
Requires-Dist: transformers==4.49.0
Requires-Dist: torchvision==0.21.0
Requires-Dist: accelerate==1.5.2
Requires-Dist: requests==2.27.1
Dynamic: author
Dynamic: author-email
Dynamic: classifier
Dynamic: description
Dynamic: description-content-type
Dynamic: download-url
Dynamic: home-page
Dynamic: keywords
Dynamic: license
Dynamic: maintainer
Dynamic: maintainer-email
Dynamic: project-url
Dynamic: requires-dist
Dynamic: requires-python
Dynamic: summary
